CHANGES.txt
LICENSE
MANIFEST.in
README.md
setup.py
pkpd/__init__.py
pkpd/bibtex.py
pkpd/biopharmaceutics.py
pkpd/constants.py
pkpd/objects.py
pkpd/pkpd_units.py
pkpd/protocols.conf
pkpd/utils.py
pkpd/wizards.py
pkpd/models/__init__.py
pkpd/models/dissolution_models.py
pkpd/models/pd_models.py
pkpd/models/pk_models.py
pkpd/models/sa_models.py
pkpd/protocols/__init__.py
pkpd/protocols/import_experiment.py
pkpd/protocols/protocol_batch_create_experiment.py
pkpd/protocols/protocol_pkpd.py
pkpd/protocols/protocol_pkpd_absorption_rate.py
pkpd/protocols/protocol_pkpd_allometric_scaling.py
pkpd/protocols/protocol_pkpd_apply_allometric_scaling.py
pkpd/protocols/protocol_pkpd_average_sample.py
pkpd/protocols/protocol_pkpd_bootstrap_simulate.py
pkpd/protocols/protocol_pkpd_change_units.py
pkpd/protocols/protocol_pkpd_change_via.py
pkpd/protocols/protocol_pkpd_compare_experiments.py
pkpd/protocols/protocol_pkpd_create_label.py
pkpd/protocols/protocol_pkpd_create_label_2exps.py
pkpd/protocols/protocol_pkpd_cumulated_dose.py
pkpd/protocols/protocol_pkpd_dissolution_deconvolve.py
pkpd/protocols/protocol_pkpd_dissolution_deconvolve_Fourier.py
pkpd/protocols/protocol_pkpd_dissolution_f2.py
pkpd/protocols/protocol_pkpd_dissolution_fit.py
pkpd/protocols/protocol_pkpd_dissolution_ivivc.py
pkpd/protocols/protocol_pkpd_dissolution_ivivc_generic.py
pkpd/protocols/protocol_pkpd_dissolution_ivivc_internal_validity.py
pkpd/protocols/protocol_pkpd_dissolution_ivivc_join.py
pkpd/protocols/protocol_pkpd_dissolution_ivivc_join_recalculate.py
pkpd/protocols/protocol_pkpd_dissolution_ivivc_splines.py
pkpd/protocols/protocol_pkpd_dissolution_levyplot.py
pkpd/protocols/protocol_pkpd_dissolution_loo_riegelman.py
pkpd/protocols/protocol_pkpd_dissolution_simulation.py
pkpd/protocols/protocol_pkpd_dissolution_wagner_nelson.py
pkpd/protocols/protocol_pkpd_dose_escalation.py
pkpd/protocols/protocol_pkpd_drop_measurements.py
pkpd/protocols/protocol_pkpd_elimination_rate.py
scipion_pkpd.egg-info/PKG-INFO
scipion_pkpd.egg-info/SOURCES.txt
scipion_pkpd.egg-info/dependency_links.txt
scipion_pkpd.egg-info/requires.txt
scipion_pkpd.egg-info/top_level.txt