Metadata-Version: 1.0
Name: scipion-pkpd
Version: 1.0.0
Summary: scipion-pkpd.
Home-page: https://github.com/cossorzano/scipion-pkpd
Author: Carlos Oscar Sorzano
Author-email: info@kinestat.com
License: UNKNOWN
Keywords: pkpd
Platform: UNKNOWN
